uraeus.nmbd.python-0.0.1.dev4-py3.7-nspkg.pth
uraeus/nmbd/python/__init__.py
uraeus/nmbd/python/codegen/__init__.py
uraeus/nmbd/python/codegen/generators.py
uraeus/nmbd/python/codegen/printer.py
uraeus/nmbd/python/codegen/projects.py
uraeus/nmbd/python/engine/__init__.py
uraeus/nmbd/python/engine/systems.py
uraeus/nmbd/python/engine/modules/__init__.py
uraeus/nmbd/python/engine/modules/vehicle_dynamics/__init__.py
uraeus/nmbd/python/engine/modules/vehicle_dynamics/tire_models.py
uraeus/nmbd/python/engine/numerics/__init__.py
uraeus/nmbd/python/engine/numerics/math_funcs/__init__.py
uraeus/nmbd/python/engine/numerics/math_funcs/geometries.py
uraeus/nmbd/python/engine/numerics/math_funcs/numba_funcs.py
uraeus/nmbd/python/engine/numerics/math_funcs/spatial_alg.py
uraeus/nmbd/python/engine/numerics/solvers/__init__.py
uraeus/nmbd/python/engine/numerics/solvers/base.py
uraeus/nmbd/python/engine/numerics/solvers/dynamics.py
uraeus/nmbd/python/engine/numerics/solvers/integrators.py
uraeus/nmbd/python/engine/numerics/solvers/kinematics.py
uraeus/nmbd/python/engine/numerics/solvers/solvers.py
uraeus/nmbd/python/engine/numerics/solvers/temp.py
uraeus/nmbd/python/engine/utilities/__init__.py
uraeus/nmbd/python/engine/utilities/decoders.py
uraeus/nmbd/python/numerics/__init__.py
uraeus/nmbd/python/numerics/core/__init__.py
uraeus/nmbd/python/numerics/core/systems.py
uraeus/nmbd/python/numerics/core/math_funcs/__init__.py
uraeus/nmbd/python/numerics/core/math_funcs/geometries.py
uraeus/nmbd/python/numerics/core/math_funcs/numba_funcs.py
uraeus/nmbd/python/numerics/core/math_funcs/spatial_alg.py
uraeus/nmbd/python/numerics/core/shared_classes/__init__.py
uraeus/nmbd/python/numerics/core/shared_classes/numcls.py
uraeus/nmbd/python/numerics/core/solvers/__init__.py
uraeus/nmbd/python/numerics/core/solvers/solvers.py
uraeus/nmbd/python/numerics/core/solvers/solvers_2.py
uraeus/nmbd/python/numerics/core/utilities/__init__.py
uraeus/nmbd/python/numerics/core/utilities/decoders.py
uraeus.nmbd.python-0.0.1.dev4.dist-info/METADATA
uraeus.nmbd.python-0.0.1.dev4.dist-info/WHEEL
uraeus.nmbd.python-0.0.1.dev4.dist-info/namespace_packages.txt
uraeus.nmbd.python-0.0.1.dev4.dist-info/top_level.txt
uraeus.nmbd.python-0.0.1.dev4.dist-info/RECORD
