Metadata-Version: 2.1
Name: uraeus.nmbd.python
Version: 0.0.1.dev4
Summary: Numerical simulation environment of constrained multi-body systems in python.
Home-page: https://github.com/khaledghobashy/uraeus-nmbd-python
Author: Khaled Ghobashy
Author-email: khaled.ghobashy@live.com
License: UNKNOWN
Platform: UNKNOWN
Classifier: Programming Language :: Python :: 3
Classifier: License :: OSI Approved :: BSD License
Classifier: Operating System :: OS Independent
Classifier: Development Status :: 1 - Planning
Classifier: Intended Audience :: Education
Classifier: Intended Audience :: Science/Research
Classifier: Topic :: Scientific/Engineering
Classifier: Topic :: Scientific/Engineering :: Physics
Classifier: Topic :: Scientific/Engineering :: Mathematics
Requires-Python: >=3.6
Requires-Dist: uraeus.smbd (>=0.0.1.dev3)
Requires-Dist: numpy
Requires-Dist: scipy
Requires-Dist: numba
Requires-Dist: pandas
